unstac/__init__.py
unstac/__main__.py
unstac-0.0.5.dist-info/LICENSE
unstac-0.0.5.dist-info/METADATA
unstac-0.0.5.dist-info/WHEEL
unstac-0.0.5.dist-info/entry_points.txt
unstac-0.0.5.dist-info/top_level.txt
unstac-0.0.5.dist-info/RECORD
