Metadata-Version: 2.1
Name: unstac
Version: 0.0.5
Summary: Tool for unwrapping Spatiotemporal Asset Catalogs into GeoPackage
Home-page: https://gitlab.com/multione/unstac
Author-email: Luka Antonić <luka.olegsson@gmail.com>
Requires-Python: >=3.10
License-File: LICENSE
Requires-Dist: pystac[orjson]
Requires-Dist: rich
Requires-Dist: typer
Requires-Dist: geopandas
Requires-Dist: shapely
